nerd_mega_compute/__init__.py
nerd_mega_compute/api.py
nerd_mega_compute/cli.py
nerd_mega_compute/config.py
nerd_mega_compute/core.py
nerd_mega_compute/spinner.py
nerd_mega_compute/utils.py
nerd_mega_compute/cloud/__init__.py
nerd_mega_compute/cloud/auth.py
nerd_mega_compute/cloud/compute.py
nerd_mega_compute/cloud/helpers.py
nerd_mega_compute/cloud/import_utils.py
nerd_mega_compute/cloud/job.py
nerd_mega_compute/cloud/on_server/__init__.py
nerd_mega_compute/cloud/on_server/on_server.py
nerd_mega_compute/cloud/on_server/templates/__init__.py
nerd_mega_compute/cloud/on_server/templates/auto_reference.py
nerd_mega_compute/cloud/on_server/templates/cloud_template.py
nerd_mega_compute/cloud/on_server/templates/execution_template.py
nerd_mega_compute/cloud/on_server/templates/universal_imports.py
nerd_mega_compute/cloud/storage/__init__.py
nerd_mega_compute/cloud/storage/data_parsing_utils.py
nerd_mega_compute/cloud/storage/data_size_utils.py
nerd_mega_compute/cloud/storage/large_download.py
nerd_mega_compute/cloud/storage/large_upload.py
nerd_mega_compute/cloud/storage/storage.py
nerd_mega_compute-0.1.62.dist-info/METADATA
nerd_mega_compute-0.1.62.dist-info/WHEEL
nerd_mega_compute-0.1.62.dist-info/entry_points.txt
nerd_mega_compute-0.1.62.dist-info/top_level.txt
nerd_mega_compute-0.1.62.dist-info/RECORD
