Metadata-Version: 2.4
Name: nerd-mega-compute
Version: 0.1.62
Summary: Run Python functions on powerful cloud servers with a simple decorator
Home-page: https://github.com/adampwright/nerd-mega-compute
Author: Adam P. Wright
Author-email: adampwright000@gmail.com
Project-URL: Bug Tracker, https://github.com/adampwright/nerd-mega-compute/issues
Classifier: Programming Language :: Python :: 3
Classifier: License :: OSI Approved :: MIT License
Classifier: Operating System :: OS Independent
Requires-Python: >=3.6
Requires-Dist: requests
Requires-Dist: python-dotenv
Dynamic: author
Dynamic: author-email
Dynamic: classifier
Dynamic: description
Dynamic: description-content-type
Dynamic: home-page
Dynamic: project-url
Dynamic: requires-dist
Dynamic: requires-python
Dynamic: summary
